usweather/USWeather.py
usweather/__init__.py
usweather-1.1.4.dist-info/METADATA
usweather-1.1.4.dist-info/WHEEL
usweather-1.1.4.dist-info/top_level.txt
usweather-1.1.4.dist-info/RECORD
